promptdump/__init__.py
promptdump/promptdump.py
promptdump-0.2.0.dist-info/METADATA
promptdump-0.2.0.dist-info/WHEEL
promptdump-0.2.0.dist-info/entry_points.txt
promptdump-0.2.0.dist-info/RECORD
