Metadata-Version: 2.4
Name: promptdump
Version: 0.2.0
Summary: A command-line tool to quickly gather and format code for AI prompts
Author: Sander Land
Requires-Python: >=3.8
Requires-Dist: pyperclip>=1.8.2
